{
  "profile": {
    "last_name": "Desai [Design]", 
    "status_emoji": "", 
    "image_1024": "https://avatars.slack-edge.com/2018-01-10/297242961605_c93de67830543a85768a_1024.jpg", 
    "display_name_normalized": "Mona", 
    "image_32": "https://avatars.slack-edge.com/2018-01-10/297242961605_c93de67830543a85768a_32.jpg", 
    "skype": "", 
    "image_72": "https://avatars.slack-edge.com/2018-01-10/297242961605_c93de67830543a85768a_72.jpg", 
    "status_expiration": 0, 
    "image_192": "https://avatars.slack-edge.com/2018-01-10/297242961605_c93de67830543a85768a_192.jpg", 
    "first_name": "Mona", 
    "display_name": "Mona", 
    "title": "UI/UX Designer", 
    "real_name_normalized": "Mona Desai [Design]", 
    "email": "mona@makeschool.com", 
    "is_custom_image": true, 
    "status_text_canonical": "", 
    "image_24": "https://avatars.slack-edge.com/2018-01-10/297242961605_c93de67830543a85768a_24.jpg", 
    "image_original": "https://avatars.slack-edge.com/2018-01-10/297242961605_c93de67830543a85768a_original.jpg", 
    "image_48": "https://avatars.slack-edge.com/2018-01-10/297242961605_c93de67830543a85768a_48.jpg", 
    "phone": "", 
    "real_name": "Mona Desai [Design]", 
    "image_512": "https://avatars.slack-edge.com/2018-01-10/297242961605_c93de67830543a85768a_512.jpg", 
    "team": "T1D4KRBR8", 
    "avatar_hash": "c93de6783054", 
    "status_text": ""
  }, 
  "updated": 1553382342, 
  "tz": "America/New_York", 
  "name": "mona", 
  "presence": "away", 
  "deleted": false, 
  "is_app_user": false, 
  "is_bot": false, 
  "tz_label": "Eastern Daylight Time", 
  "real_name": "Mona Desai [Design]", 
  "color": "e0a729", 
  "team_id": "T1D4KRBR8", 
  "is_admin": true, 
  "is_ultra_restricted": false, 
  "is_restricted": false, 
  "tz_offset": -14400, 
  "is_primary_owner": false, 
  "id": "U4CEBV4SW", 
  "is_owner": false
}